client/__init__.py
client/main.py
fdr_dev2-0.2.0.dist-info/METADATA
fdr_dev2-0.2.0.dist-info/WHEEL
fdr_dev2-0.2.0.dist-info/entry_points.txt
fdr_dev2-0.2.0.dist-info/top_level.txt
fdr_dev2-0.2.0.dist-info/RECORD
