Metadata-Version: 2.1
Name: fdr-dev2
Version: 0.2.0
Summary: Sample fdr lib
Author: Konstantinos Gyftodimos
Author-email: konstgyftodimos@gmail.com
